email_decomposer/EmailDecomposer.py
email_decomposer/FullName.py
email_decomposer/__init__.py
email_decomposer/resources/Names_2010Census.txt
email_decomposer/resources/dist.female.first.txt
email_decomposer/resources/dist.male.first.txt
tests/__init__.py
tests/common.py
tests/mocks_generator.py
tests/test_EmailDecomposer.py
tests/test_mocks_generator.py
email_decomposer-0.0.4.dist-info/LICENSE
email_decomposer-0.0.4.dist-info/METADATA
email_decomposer-0.0.4.dist-info/WHEEL
email_decomposer-0.0.4.dist-info/top_level.txt
email_decomposer-0.0.4.dist-info/RECORD
