Metadata-Version: 2.1
Name: email-decomposer
Version: 0.0.4
Summary: Fuzzy decomposition of email prefix to first/last name
Home-page: https://github.com/intuit/email-decomposer
Author: Elhanan Mishraky
Author-email: elhanan_mishraky@intuit.com
License: Apache License 2.0
Classifier: Development Status :: 5 - Production/Stable
Classifier: License :: OSI Approved :: Apache Software License
Classifier: Programming Language :: Python :: 3.6
Classifier: Topic :: Software Development :: Libraries
Classifier: Topic :: Software Development :: Libraries :: Python Modules
Classifier: Intended Audience :: Developers
Classifier: Operating System :: OS Independent
Requires-Python: >=3.6
License-File: LICENSE
Requires-Dist: pandas (>=1.1.5)
Requires-Dist: numpy (>=1.19.4)
Requires-Dist: nltk (==3.8.1)
Provides-Extra: test
Requires-Dist: names (>=0.3.0) ; extra == 'test'
Requires-Dist: pytest ; extra == 'test'
